.gitignore
README.md
readout.py
setup.py
readout.egg-info/PKG-INFO
readout.egg-info/SOURCES.txt
readout.egg-info/dependency_links.txt
readout.egg-info/entry_points.txt
readout.egg-info/requires.txt
readout.egg-info/top_level.txt