Metadata-Version: 1.1
Name: readout
Version: 0.1.1
Summary: A framework for detecting changes and reacting to them.
Home-page: https://github.com/lainproliant/readout
Author: Lain Musgrove (lainproliant)
Author-email: lain.proliant@gmail.com
License: MIT
Keywords: monitoring framework API
Platform: UNKNOWN
Classifier: Intended Audience :: Developers
Classifier: Topic :: Software Development :: Libraries :: Application Frameworks
Classifier: License :: OSI Approved :: BSD License
Classifier: Programming Language :: Python :: 3
Classifier: Programming Language :: Python :: 3.8
